Workbook

Sheet 总览
A1: Future flow，PMF 阶段期权分红 | B1: Future flow，PMF 阶段期权分红 | C1: Future flow，PMF 阶段期权分红 | D1: Future flow，PMF 阶段期权分红 | E1: Future flow，PMF 阶段期权分红 | F1: Future flow，PMF 阶段期权分红 | G1: Future flow，PMF 阶段期权分红 | H1: Future flow，PMF 阶段期权分红 | I1: Future flow，PMF 阶段期权分红 | J1: Future flow，PMF 阶段期权分红
A2: Future flow，PMF 阶段期权分红 | B2: Future flow，PMF 阶段期权分红 | C2: Future flow，PMF 阶段期权分红 | D2: Future flow，PMF 阶段期权分红 | E2: Future flow，PMF 阶段期权分红 | F2: Future flow，PMF 阶段期权分红 | G2: Future flow，PMF 阶段期权分红 | H2: Future flow，PMF 阶段期权分红 | I2: Future flow，PMF 阶段期权分红 | J2: Future flow，PMF 阶段期权分红
A4: 本版只先确定整体比例，不锁定 Founder（创始人）和 Co-founder（联合创始人）人数。PMF（Product-Market Fit，产品市场匹配）阶段以验证客户、收入、交付和回款为核心，联合创始人通过更高期权池 + 基本工资获得激励，创始人暂不拿工资。
A8: 整体池子比例｜先定池子，不定人数 | B8: 整体池子比例｜先定池子，不定人数 | C8: 整体池子比例｜先定池子，不定人数 | D8: 整体池子比例｜先定池子，不定人数 | E8: 整体池子比例｜先定池子，不定人数 | F8: 整体池子比例｜先定池子，不定人数 | G8: 整体池子比例｜先定池子，不定人数 | H8: 整体池子比例｜先定池子，不定人数 | I8: 整体池子比例｜先定池子，不定人数 | J8: 整体池子比例｜先定池子，不定人数
A9: 池子 | B9: 比例 | C9: 人数 | D9: 薪资待遇 | E9: 用途 | F9: 核心规则 | H9: 池子 | I9: 比例百分点
A10: Founder Pool（创始人池） | B10: =股权池规则!B6 -> 0.6 | C10: 待定 | D10: No salary（无基本工资） | E10: 控制权、融资、方向和核心责任 | F10: 4-5 年 Vesting（归属），12 个月 Cliff（悬崖期） | H10: Founder | I10: 60
A11: Co-founder Option Pool（联合创始人期权池） | B11: =股权池规则!B7 -> 0.3 | C11: 待定 | D11: Base salary（有基本工资） | E11: PMF 验证、客户签约、交付和回款 | F11: 4-5 年 Vesting（归属），12 个月 Cliff（悬崖期） | H11: Co-founder | I11: 30
A12: Employee ESOP（员工期权池） | B12: =股权池规则!B8 -> 0.1 | C12: 未来员工 | D12: 按岗位薪资 | E12: 未来核心员工和关键岗位 | F12: 10% 即可，后续融资前再评估是否补池 | H12: Employee ESOP | I12: 10
A13: 合计 | B13: =SUM(B10:B12) -> 1 | H13: 合计 | I13: 100
A33: 一句话规则 | B33: 一句话规则 | C33: 一句话规则 | D33: 一句话规则 | E33: 一句话规则 | F33: 一句话规则 | G33: 一句话规则 | H33: 一句话规则 | I33: 一句话规则 | J33: 一句话规则
A34: 1. 人数待定，先锁定三大池子：Founder Pool（创始人池）60%、Co-founder Option Pool（联合创始人期权池）30%、Employee ESOP（员工期权池）10%。
A35: 2. Founder（创始人）无基本工资，主要通过 Founder Pool（创始人池）和融资补偿机制体现前期投入。
A36: 3. Co-founder（联合创始人）有基本工资，同时从 Co-founder Option Pool（联合创始人期权池）中按贡献分配。
A37: 4. Vesting（归属）建议 4-5 年，Cliff（悬崖期）12 个月；未到归属条件，不应一次性拿完。
A38: 5. No Leaver Repurchase（无离职回购）：不设置公司花钱回购安排；已归属部分保留，未归属部分停止继续归属或按协议失效。
A39: 6. PMF 阶段默认不分红，现金优先用于增长；确需分红时，按已归属且有分红权的实股/期权行权后权益比例分配。

Sheet 股权池规则
A1: Future flow，PMF 阶段期权分红 | B1: Future flow，PMF 阶段期权分红 | C1: Future flow，PMF 阶段期权分红 | D1: Future flow，PMF 阶段期权分红 | E1: Future flow，PMF 阶段期权分红 | F1: Future flow，PMF 阶段期权分红 | G1: Future flow，PMF 阶段期权分红 | H1: Future flow，PMF 阶段期权分红
A2: Future flow，PMF 阶段期权分红 | B2: Future flow，PMF 阶段期权分红 | C2: Future flow，PMF 阶段期权分红 | D2: Future flow，PMF 阶段期权分红 | E2: Future flow，PMF 阶段期权分红 | F2: Future flow，PMF 阶段期权分红 | G2: Future flow，PMF 阶段期权分红 | H2: Future flow，PMF 阶段期权分红
A4: 三大池子｜黄色比例可调整 | B4: 三大池子｜黄色比例可调整 | C4: 三大池子｜黄色比例可调整 | D4: 三大池子｜黄色比例可调整 | E4: 三大池子｜黄色比例可调整 | F4: 三大池子｜黄色比例可调整 | G4: 三大池子｜黄色比例可调整 | H4: 三大池子｜黄色比例可调整
A5: 池子 | B5: 比例 | C5: 人数 | D5: 薪资待遇 | E5: 分配对象 | F5: 归属期 | G5: 悬崖期 | H5: 备注
A6: Founder Pool（创始人池） | B6: 0.6 | C6: 待定 | D6: No salary（无基本工资） | E6: 六哥+技术合伙人+资方 | F6: 48-60 months（4-5年） | G6: 12 months（12个月） | H6: 承担方向、融资、控制权和最终责任
A7: Co-founder Option Pool（联合创始人期权池） | B7: 0.3 | C7: 待定 | D7: Base salary（有基本工资） | E7: 小燕，杰哥，雨潼，宁可，阿金 | F7: 48-60 months（4-5年） | G7: 12 months（12个月） | H7: 按 PMF 贡献、签约、交付、回款分配
A8: Employee ESOP（员工期权池） | B8: 0.1 | C8: 未来员工 | D8: 按岗位薪资 | E8: 未来核心员工 | F8: 48 months（4年） | G8: 12 months（12个月） | H8: 10% 先够用，融资前再评估
A9: 合计 | B9: =SUM(B6:B8) -> 1
A12: 未来分配口径｜现在不填人名也能用 | B12: 未来分配口径｜现在不填人名也能用 | C12: 未来分配口径｜现在不填人名也能用 | D12: 未来分配口径｜现在不填人名也能用 | E12: 未来分配口径｜现在不填人名也能用 | F12: 未来分配口径｜现在不填人名也能用 | G12: 未来分配口径｜现在不填人名也能用 | H12: 未来分配口径｜现在不填人名也能用
A13: 维度 | B13: Founder Pool（创始人池） | C13: Co-founder Option Pool（联合创始人期权池） | D13: Employee ESOP（员工期权池） | E13: 解释
A14: 全职投入 | B14: 必须 | C14: 原则上必须 | D14: 按岗位 | E14: 兼职人员不应按全职比例获得核心池份额
A15: 客户/收入结果 | B15: 强相关 | C15: 强相关 | D15: 岗位相关 | E15: PMF 阶段最重要的是签约、回款、留存和交付
A16: 不可替代性 | B16: 极高 | C16: 较高 | D16: 一般到较高 | E16: 越不可替代，越应从对应池子中获得更高份额
A17: 薪资补偿 | B17: 无工资，靠融资补偿 | C17: 有基本工资 | D17: 正常工资 | E17: 薪资和期权需要合并看总激励
A18: 分红资格 | B18: 已归属/有实股权后 | C18: 已归属/行权后 | D18: 已授予/归属/行权后 | E18: 未行权或未归属部分不参与现金分红
A19: 离职安排 | B19: 无离职回购 | C19: 无离职回购 | D19: 无离职回购 | E19: 已归属保留，未归属停止继续归属或按协议失效

Sheet 融资补偿
A1: Future flow，PMF 阶段期权分红 | B1: Future flow，PMF 阶段期权分红 | C1: Future flow，PMF 阶段期权分红 | D1: Future flow，PMF 阶段期权分红 | E1: Future flow，PMF 阶段期权分红 | F1: Future flow，PMF 阶段期权分红 | G1: Future flow，PMF 阶段期权分红 | H1: Future flow，PMF 阶段期权分红
A2: Future flow，PMF 阶段期权分红 | B2: Future flow，PMF 阶段期权分红 | C2: Future flow，PMF 阶段期权分红 | D2: Future flow，PMF 阶段期权分红 | E2: Future flow，PMF 阶段期权分红 | F2: Future flow，PMF 阶段期权分红 | G2: Future flow，PMF 阶段期权分红 | H2: Future flow，PMF 阶段期权分红
A4: 融资补偿建议单独处理，不要偷偷塞进股权比例里。Founder（创始人）前期无工资，可设置 Deferred Compensation（递延补偿）或 Qualified Financing Bonus（合格融资奖金），但必须有上限、审批和现金安全条件。
A7: 融资补偿机制｜黄色数字可改 | B7: 融资补偿机制｜黄色数字可改 | C7: 融资补偿机制｜黄色数字可改 | D7: 融资补偿机制｜黄色数字可改 | E7: 融资补偿机制｜黄色数字可改 | F7: 融资补偿机制｜黄色数字可改 | G7: 融资补偿机制｜黄色数字可改 | H7: 融资补偿机制｜黄色数字可改
A8: 项目 | B8: 输入 / 计算 | C8: 说明 | D8: 投资人视角
A9: Qualified Financing（合格融资金额） | B9: ¥10,000,000基准单位 | C9: 例如完成外部机构融资 | D9: 融资后才触发，不提前形成现金压力
A10: Founder Deferred Compensation Cap（创始人递延补偿上限） | B10: 600000 | C10: 创始人无工资期间的补偿上限 | D10: 建议有上限，避免变成隐性债务
A11: Compensation Trigger（触发条件） | B11: 融资到账 | C11: 不是口头承诺 | D11: 治理清楚
A13: Suggested Founder Compensation Pool（建议创始人补偿池） | B13: 500000 | C13: MIN（融资额5%，补偿上限只限首轮） | D13: 合理但克制
A14: Co-founder Salary（联合创始人工资） | B14: 按月发放 | C14: 联合创始人已有基本工资 | D14: 不再重复计入融资补偿
A15: Equity Compensation（股权补偿） | B15: 不额外增加 | C15: 股权已体现在 30% 联合创始人期权池 | D15: 避免融资前 cap table（股权表）混乱
A18: 补偿分配规则 | B18: 补偿分配规则 | C18: 补偿分配规则 | D18: 补偿分配规则 | E18: 补偿分配规则 | F18: 补偿分配规则 | G18: 补偿分配规则 | H18: 补偿分配规则
A19: 对象 | B19: 是否参与融资补偿 | C19: 理由 | D19: 建议
A20: Founder（创始人） | B20: Yes / 是 | C20: 前期无工资，承担融资和公司方向责任 | D20: 从补偿池中按实际未发薪、投入和董事会批准分配
A21: Co-founder（联合创始人） | B21: Usually No / 通常否 | C21: 已有基本工资，另有 30% 期权池 | D21: 除非有明确未支付工资或特别贡献，否则不重复补偿
A22: Employee（员工） | B22: No / 否 | C22: 员工走工资和 ESOP（员工期权池） | D22: 不参与创始人融资补偿池
A23: Company（公司） | B23: Priority / 优先 | C23: 现金优先用于增长和交付 | D23: 补偿不得损害现金安全

Sheet 分红计算
A1: Future flow，PMF 阶段期权分红 | B1: Future flow，PMF 阶段期权分红 | C1: Future flow，PMF 阶段期权分红 | D1: Future flow，PMF 阶段期权分红 | E1: Future flow，PMF 阶段期权分红 | F1: Future flow，PMF 阶段期权分红 | G1: Future flow，PMF 阶段期权分红 | H1: Future flow，PMF 阶段期权分红
A2: Future flow，PMF 阶段期权分红 | B2: Future flow，PMF 阶段期权分红 | C2: Future flow，PMF 阶段期权分红 | D2: Future flow，PMF 阶段期权分红 | E2: Future flow，PMF 阶段期权分红 | F2: Future flow，PMF 阶段期权分红 | G2: Future flow，PMF 阶段期权分红 | H2: Future flow，PMF 阶段期权分红
A4: 分红池｜PMF 阶段默认 0% | B4: 分红池｜PMF 阶段默认 0% | C4: 分红池｜PMF 阶段默认 0% | D4: 分红池｜PMF 阶段默认 0%
A5: 项目 | B5: 输入 / 计算 | C5: 说明
A6: 税后利润 | B6: 1000000 | C6: 示例值，可修改
A7: 留存及公积金比例 | B7: 0.35 | C7: 先留存现金，正式执行以法律和财务意见为准
A8: 可分配利润 | B8: =B6*(1-B7) -> 650000 | C8: 税后利润 ×（1－留存比例）
A9: 现金分红比例 | B9: 0.3 | C9: PMF 阶段默认 0%；成熟后可调整
A10: 实际现金分红池 | B10: =B8*B9 -> 195000 | C10: 可分配利润 × 分红比例
A11: 公司留存利润 | B11: =B6-B10 -> 805000 | C11: 税后利润－实际现金分红
A13: 按三大池子分红｜未归属/未行权部分不参与 | B13: 按三大池子分红｜未归属/未行权部分不参与 | C13: 按三大池子分红｜未归属/未行权部分不参与 | D13: 按三大池子分红｜未归属/未行权部分不参与 | E13: 按三大池子分红｜未归属/未行权部分不参与 | F13: 按三大池子分红｜未归属/未行权部分不参与 | G13: 按三大池子分红｜未归属/未行权部分不参与 | H13: 按三大池子分红｜未归属/未行权部分不参与
A14: 池子 | B14: 池子比例 | C14: 当前可分红权重 | D14: 现金分红 | E14: PMF 默认结果 | F14: 规则 | G14: 备注
A15: Founder Pool（创始人池） | B15: =股权池规则!B6 -> 0.6 | C15: =B15/(B15+B16) -> 0.66666667 | D15: =$B$10*C15 -> 130000 | E15: =IF($B$9=0,"¥0（不分红）",D15) -> 130000 | F15: 已归属/有实股权后参与 | G15: 创始人暂无工资，可另看融资补偿
A16: Co-founder Option Pool（联合创始人期权池） | B16: =股权池规则!B7 -> 0.3 | C16: =B16/(B15+B16) -> 0.33333333 | D16: =$B$10*C16 -> 65000 | E16: =IF($B$9=0,"¥0（不分红）",D16) -> 65000 | F16: 已归属/行权后参与 | G16: 联合创始人有基本工资
A17: Employee ESOP（员工期权池） | B17: =股权池规则!B8 -> 0.1 | C17: 0 | D17: =$B$10*C17 -> 0 | E17: =IF($B$9=0,"¥0（不分红）",D17) -> 0 | F17: 未授予/未行权不分红 | G17: 员工期权池先保留 10%
A18: 合计 | B18: =SUM(B15:B17) -> 1 | C18: =SUM(C15:C17) -> 1 | D18: =SUM(D15:D17) -> 195000

Sheet 公式检查
A1: Future flow，PMF 阶段期权分红 | B1: Future flow，PMF 阶段期权分红 | C1: Future flow，PMF 阶段期权分红 | D1: Future flow，PMF 阶段期权分红 | E1: Future flow，PMF 阶段期权分红 | F1: Future flow，PMF 阶段期权分红
A2: Future flow，PMF 阶段期权分红 | B2: Future flow，PMF 阶段期权分红 | C2: Future flow，PMF 阶段期权分红 | D2: Future flow，PMF 阶段期权分红 | E2: Future flow，PMF 阶段期权分红 | F2: Future flow，PMF 阶段期权分红
A4: 检查项 | B4: 实际 | C4: 目标 | D4: 差异 | E4: 容忍度 | F4: 状态
A5: 总池子比例 | B5: =股权池规则!B9 -> 1 | C5: 1 | D5: =B5-C5 -> 0 | E5: 0.0001 | F5: =IF(ABS(D5)<=E5,"OK / 通过","CHECK / 检查") -> OK / 通过
A6: Founder Pool（创始人池） | B6: =股权池规则!B6 -> 0.6 | C6: 0.6 | D6: =B6-C6 -> 0 | E6: 0.0001 | F6: =IF(ABS(D6)<=E6,"OK / 通过","CHECK / 检查") -> OK / 通过
A7: Co-founder Option Pool（联合创始人期权池） | B7: =股权池规则!B7 -> 0.3 | C7: 0.3 | D7: =B7-C7 -> 0 | E7: 0.0001 | F7: =IF(ABS(D7)<=E7,"OK / 通过","CHECK / 检查") -> OK / 通过
A8: Employee ESOP（员工期权池） | B8: =股权池规则!B8 -> 0.1 | C8: 0.1 | D8: =B8-C8 -> 0 | E8: 0.0001 | F8: =IF(ABS(D8)<=E8,"OK / 通过","CHECK / 检查") -> OK / 通过
A9: 分红分配合计 | B9: =分红计算!D18 -> 195000 | C9: =分红计算!B10 -> 195000 | D9: =B9-C9 -> 0 | E9: 1 | F9: =IF(ABS(D9)<=E9,"OK / 通过","CHECK / 检查") -> OK / 通过
